pyPeriod/Periods.py
pyPeriod/QOPeriods.py
pyPeriod/RamanujanPeriods.py
pyPeriod/__init__.py
pyPeriod/extra.py
pyPeriod-0.2.4.dist-info/LICENSE
pyPeriod-0.2.4.dist-info/METADATA
pyPeriod-0.2.4.dist-info/WHEEL
pyPeriod-0.2.4.dist-info/top_level.txt
pyPeriod-0.2.4.dist-info/RECORD
