Metadata-Version: 2.1
Name: pyPeriod
Version: 0.2.4
Summary: Periodicity Transforms in Python (Sethares and Staley, Ramanujan, my own)
Home-page: https://github.com/woolgathering/pyPeriod
Author: Jacob Sundstrom
Author-email: jacob.sundstrom@gmail.com
License: UNKNOWN
Platform: UNKNOWN
Classifier: Programming Language :: Python :: 3
Classifier: License :: OSI Approved :: MIT License
Classifier: Operating System :: OS Independent
Requires-Python: >=3.6
License-File: LICENSE
Requires-Dist: numpy
Requires-Dist: scipy
